promptdefend_mcp/__init__.py
promptdefend_mcp-1.0.0.dist-info/METADATA
promptdefend_mcp-1.0.0.dist-info/WHEEL
promptdefend_mcp-1.0.0.dist-info/entry_points.txt
promptdefend_mcp-1.0.0.dist-info/RECORD
