Metadata-Version: 2.4
Name: promptdefend-mcp
Version: 1.0.0
Summary: Prompt Defend MCP Server - 16-Layer Guardrails for AI Agents
Project-URL: Homepage, https://promptdefend.dev
Project-URL: Documentation, https://docs.promptdefend.dev
Author-email: Prompt Defend <support@promptdefend.dev>
License: Proprietary
Keywords: ai,guardrails,llm,mcp,promptdefend,security
Classifier: Development Status :: 5 - Production/Stable
Classifier: Intended Audience :: Developers
Classifier: License :: Other/Proprietary License
Classifier: Programming Language :: Python :: 3
Classifier: Programming Language :: Python :: 3.10
Classifier: Programming Language :: Python :: 3.11
Classifier: Programming Language :: Python :: 3.12
Classifier: Topic :: Security
Requires-Python: >=3.10
Requires-Dist: httpx>=0.25.0
Requires-Dist: mcp>=1.0.0
